numerous/cli/.exclude
numerous/cli/__init__.py
numerous/cli/__main__.py
numerous/cli/auth.py
numerous/cli/build_manager_client.py
numerous/cli/client.py
numerous/cli/job.py
numerous/cli/local.py
numerous/cli/repository.py
numerous/cli/run.py
numerous/cli/utils.py
numerous/cli/commands/__init__.py
numerous/cli/commands/build.py
numerous/cli/commands/checkout.py
numerous/cli/commands/clone.py
numerous/cli/commands/config.py
numerous/cli/commands/init.py
numerous/cli/commands/log.py
numerous/cli/commands/login.py
numerous/cli/commands/push.py
numerous/cli/commands/version.py
numerous/client/__init__.py
numerous/client/common.py
numerous/client/config.py
numerous/client/data_source.py
numerous/client/numerous_admin_client.py
numerous/client/numerous_buffered_writer.py
numerous/client/numerous_client.py
numerous/client/numerous_log_handler.py
numerous/client/utils.py
numerous/client/optimization/__init__.py
numerous/client/optimization/configuration.py
numerous/client/optimization/orchestrator.py
numerous/client_common/__init__.py
numerous/client_common/grpc_retry.py
numerous/client_common/request_response_stream.py
numerous/client_common/validation_interceptor.py
numerous/image_tools/__init__.py
numerous/image_tools/app.py
numerous/image_tools/errors.py
numerous/image_tools/job.py
numerous/image_tools/system.py
numerous/image_tools/example_models/__init__.py
numerous/image_tools/example_models/multiply_by_two/__init__.py
numerous/image_tools/example_models/multiply_by_two/model.py
numerous/image_tools/examples/__init__.py
numerous/image_tools/examples/multiply_by_two.py
numerous/sdk/__init__.py
numerous/sdk/py.typed
numerous/sdk/utils.py
numerous/sdk/connect/__init__.py
numerous/sdk/connect/access_token.py
numerous/sdk/connect/auth.py
numerous/sdk/connect/command_handler.py
numerous/sdk/connect/config.py
numerous/sdk/connect/file_manager.py
numerous/sdk/connect/hibernation.py
numerous/sdk/connect/inputs.py
numerous/sdk/connect/job_client.py
numerous.sdk-1.6.1.dist-info/LICENSE.txt
numerous.sdk-1.6.1.dist-info/METADATA
numerous.sdk-1.6.1.dist-info/WHEEL
numerous.sdk-1.6.1.dist-info/entry_points.txt
numerous.sdk-1.6.1.dist-info/top_level.txt
numerous.sdk-1.6.1.dist-info/RECORD
