Metadata-Version: 2.1
Name: numerous.sdk
Version: 1.6.1
License: MIT License
Project-URL: Homepage, https://numerous.com
Project-URL: Repository, https://gitlab.com/numerous/numerous.sdk
Project-URL: Documentation, https://numeroussdk.readthedocs.io
Project-URL: Changelog, https://gitlab.com/numerous/numerous.sdk/-/blob/main/CHANGELOG.md
Classifier: Programming Language :: Python :: 3
Classifier: License :: OSI Approved :: MIT License
Classifier: Operating System :: OS Independent
Requires-Python: >=3.9
License-File: LICENSE.txt
Requires-Dist: colorama >=0.4.4
Requires-Dist: grpc-interceptor ==0.13.0
Requires-Dist: grpcio >=1.56.2
Requires-Dist: ipywidgets <9,>=8.0.4
Requires-Dist: jinja2 <4,>=3.1.2
Requires-Dist: networkx <4,>=3.0
Requires-Dist: numerous.grpc >=1.1.0
Requires-Dist: pathspec >=0.11.1
Requires-Dist: plotly <6,>=5.13.0
Requires-Dist: prettytable <4,>=3.6.0
Requires-Dist: protobuf >=4.24
Requires-Dist: requests <3,>=2.28.2
Requires-Dist: str2bool <2,>=1.1
Provides-Extra: lint
Requires-Dist: pre-commit ==3.3.3 ; extra == 'lint'
Requires-Dist: flake8 ==6.0.0 ; extra == 'lint'
Requires-Dist: flake8-pyproject ==1.2.2 ; extra == 'lint'
Requires-Dist: black ==23.1.0 ; extra == 'lint'
Requires-Dist: isort ==5.12.0 ; extra == 'lint'
Requires-Dist: vulture ==2.7 ; extra == 'lint'
Requires-Dist: bandit ==1.7.4 ; extra == 'lint'
Requires-Dist: mypy ==1.0.0 ; extra == 'lint'
Requires-Dist: types-requests ==2.28.11.12 ; extra == 'lint'
Requires-Dist: types-setuptools ==67.2.0.1 ; extra == 'lint'
Requires-Dist: types-protobuf ==4.24.0.4 ; extra == 'lint'
Provides-Extra: test
Requires-Dist: pytest ==7.2.1 ; extra == 'test'
Requires-Dist: pytest-mock ==3.10.0 ; extra == 'test'
Requires-Dist: coverage ==7.1.0 ; extra == 'test'
Requires-Dist: scipy >=1.12 ; extra == 'test'
Requires-Dist: time-machine ==2.13.0 ; extra == 'test'
Requires-Dist: pandas <3 ; extra == 'test'
Requires-Dist: numpy <1.26,>=1.24.2 ; (python_version < "3.12") and extra == 'test'
Requires-Dist: numpy >=1.26 ; (python_version >= "3.12") and extra == 'test'
